crossformer/__init__.py
crossformer/data_tools/__init__.py
crossformer/data_tools/data_interface.py
crossformer/model/__init__.py
crossformer/model/crossformer.py
crossformer/model/layers/__init__.py
crossformer/model/layers/attention.py
crossformer/model/layers/decoder.py
crossformer/model/layers/embedding.py
crossformer/model/layers/encoder.py
crossformer/utils/__init__.py
crossformer/utils/metrics.py
crossformer/utils/tools.py
crossformer-1.5.0.dist-info/licenses/LICENSE
crossformer-1.5.0.dist-info/METADATA
crossformer-1.5.0.dist-info/WHEEL
crossformer-1.5.0.dist-info/top_level.txt
crossformer-1.5.0.dist-info/RECORD
