Metadata-Version: 2.4
Name: crossformer
Version: 1.5.0
Summary: CrossFormer for multivariate time series forecasting
Home-page: https://github.com/Sedimark/Surrey_AI
Author: Dr. Peipei Wu (Paul)
Author-email: peipeiwu1996@gmail.com
License: EUPL-1.2
Classifier: Programming Language :: Python :: 3
Classifier: Operating System :: OS Independent
Requires-Python: >=3.7
License-File: LICENSE
Requires-Dist: torch
Requires-Dist: lightning
Requires-Dist: pandas
Provides-Extra: dev
Requires-Dist: pytest; extra == "dev"
Dynamic: author
Dynamic: author-email
Dynamic: classifier
Dynamic: description
Dynamic: description-content-type
Dynamic: home-page
Dynamic: license
Dynamic: license-file
Dynamic: provides-extra
Dynamic: requires-dist
Dynamic: requires-python
Dynamic: summary
